cellbin2/__init__.py
cellbin2/cellbin_pipeline.py
cellbin2/config/Stereo-CITE_T_FF.json
cellbin2/config/Stereo-CITE_T_FF_R.json
cellbin2/config/Stereo-seq_N_FFPE.json
cellbin2/config/Stereo-seq_N_FFPE_R.json
cellbin2/config/Stereo-seq_T_FF.json
cellbin2/config/Stereo-seq_T_FF_R.json
cellbin2/config/cellbin.yaml
cellbin2/config/chip_mask.json
cellbin2/config/weights_url.json
cellbin2/contrib/__init__.py
cellbin2/contrib/base_module.py
cellbin2/contrib/calibration.py
cellbin2/contrib/cell_filter.py
cellbin2/contrib/cell_segmentor.py
cellbin2/contrib/cellpose_segmentor.py
cellbin2/contrib/chip_detector.py
cellbin2/contrib/chip_transform.py
cellbin2/contrib/clarity.py
cellbin2/contrib/fast_correct.py
cellbin2/contrib/gmm_correct.py
cellbin2/contrib/mask_manager.py
cellbin2/contrib/multimodal_cell_merge.py
cellbin2/contrib/param.py
cellbin2/contrib/tissue_segmentor.py
cellbin2/contrib/track_align.py
cellbin2/contrib/alignment/__init__.py
cellbin2/contrib/alignment/basic.py
cellbin2/contrib/alignment/chip_box.py
cellbin2/contrib/alignment/template_00pt.py
cellbin2/contrib/alignment/template_centroid.py
cellbin2/contrib/stitch/setup.py
cellbin2/contrib/stitch/mfws/__init__.py
cellbin2/contrib/stitch/mfws/main.py
cellbin2/contrib/stitch/mfws/modules/__init__.py
cellbin2/contrib/stitch/mfws/modules/fov_aligner.py
cellbin2/contrib/stitch/mfws/modules/global_location.py
cellbin2/contrib/stitch/mfws/modules/jitter_correct.py
cellbin2/contrib/stitch/mfws/modules/scan_method.py
cellbin2/contrib/stitch/mfws/modules/stitching.py
cellbin2/contrib/stitch/mfws/modules/wsi_stitch.py
cellbin2/contrib/template/__init__.py
cellbin2/contrib/template/inference.py
cellbin2/contrib/template/point_detector.py
cellbin2/contrib/template/track_qc.py
cellbin2/contrib/template/inferencev1/__init__.py
cellbin2/contrib/template/inferencev1/inference_v1.py
cellbin2/contrib/template/inferencev1/line_detector.py
cellbin2/contrib/template/inferencev1/roi_picker.py
cellbin2-1.1.2.dist-info/LICENSE
cellbin2-1.1.2.dist-info/METADATA
cellbin2-1.1.2.dist-info/WHEEL
cellbin2-1.1.2.dist-info/top_level.txt
cellbin2-1.1.2.dist-info/RECORD
